{
  "version": 1,
  "updatedAt": "2026-05-12T14:00:52.512-05:00",
  "lastLink": "https://cyberpress.org/best-xdr-solutions/",
  "lastId": "1ic9q00000",
  "lastFilePath": "cyberpress/pages/2026/05/12/top-10-best-xdr-extended-detection-and-response-solutions-in-2026.md",
  "items": [
    {
      "id": "1ic9q00000",
      "link": "https://cyberpress.org/best-xdr-solutions/",
      "filePath": "cyberpress/pages/2026/05/12/top-10-best-xdr-extended-detection-and-response-solutions-in-2026.md",
      "committedAt": "2026-05-12T14:00:52.512-05:00",
      "title": "Top 10 Best XDR (Extended Detection and Response) Solutions in 2026"
    }
  ]
}