{
  "version": 1,
  "updatedAt": "2026-02-13T11:00:37.702-05:00",
  "lastLink": "https://cyberpress.org/orb-networks-masks-attacks/",
  "lastId": "ytwz440000",
  "lastFilePath": "cyberpress/pages/2026/02/13/orb-networks-leverages-compromised-iot-devices-for-masked-cyberattacks.md",
  "items": [
    {
      "id": "ytwz440000",
      "link": "https://cyberpress.org/orb-networks-masks-attacks/",
      "filePath": "cyberpress/pages/2026/02/13/orb-networks-leverages-compromised-iot-devices-for-masked-cyberattacks.md",
      "committedAt": "2026-02-13T11:00:37.702-05:00",
      "title": "ORB Networks Leverages Compromised IoT Devices for Masked Cyberattacks"
    }
  ]
}